{
  "submittedAt": "2025-10-30T18:47:44.998000",
  "email": "bakafenxiguan@gmail.com",
  "supportResponse": "자기소개\n편의점, 홈플러스, 다이소에서 일하다가 꿈을 쫒고 싶은 마음이 강해졌습니다.\n그래서 가장 좋아하던 게임 혹은 문학에 마지막으로 불 태워보고 싶어 이곳저곳 찾다가\n가장 평가가 좋은 이곳에 지원하게 되었습니다.\n\n지원 동기\n꿈과 전혀 상관없는 근무 그리고 백수로 한심스럽게 긴 시간을 보냈기에\n정말 마지막이라는 생각으로 그동안 잃어버린 노력과 흥미를 다시 되살려 내 꿈인 게임 관련 직장을 다니기 위해 지원하게 되었습니다.\n\n관련 경험\n아쉽지만 없습니다.\n\n희망 분야\n레벨 디자인, 스토리 기획자, 이벤트 기획자, 던전 기획자\n\n수료 목표\n수료 후 게임 업계에 취직해 점점 나아가 제 꿈의 직장인 넥슨에 들어가 이름을 알리고 싶습니다.\n\n갈등 대응\n상황을 피하는 경향\n\n실패 대응\n배움과 성장으로 받아들임\n\n타인 대응\n타인에게 엄격한 편이지만 굳이 얘기하지 않음",
  "interviewScore": 65,
  "interviewResult": "합격",
  "interviewSummary": "[화상 인터뷰 합격]\n\n서브컬쳐를 매우 좋아하는 사람이라고 소개했습니다.\n이전에 공부를 너무 안해서, 마지막 기회라는 심정으로 게임 기획자 과정에 지원했다고 합니다.\n캐릭터, 시나리오 기획 쪽에 관심이 많은데, 그 중에서도 특히 시나리오 기획자가 되려면 '글을 얼마나 잘 써야 하는지' 에 대한 질문이 있었습니다.\nMS Office나 AI는 거의 사용해본적이 없다고 합니다.\n대화가 약간 어려운 정도로 낯을 매우 많이 가립니다.\n말을 잘 못합니다.\n수업을 따라오는데 어느 정도 난항이 예상됩니다."
}
