[
  {
    "retroId": "retro-7a43c7925614",
    "phase": "1차 프로젝트",
    "date": "2026-01-27",
    "originalDate": "2026-01-27",
    "submittedAt": "2026-01-27T11:57:04.687000",
    "detail": "기획에 대하여\n공동으로 회의한 내용에서 생략되거나 변화된 요소가 많았습니다.\n이 과정에서 실시간으로 공유 및 안내를 진행하였지만, 작업자들이 해당 사항을 제대로 이해했는지 확인이 미흡했습니다. \n\n기획서는 거의 없었다고 볼 수 있었습니다. 스토리 문서를 기획서로 생각하며 진행했었는데, 점차 스토리 문서는 스크립트 정리본이 되어가면서 명확한 설명이나 묘사가 사라진 점이 그 원인입니다.\n\n협업에 대하여\n프로젝트 중에 작업물은 실시간으로 공유하며 변동 사항에 대해서 공지 해왔었습니다.\n그 과정에서 적극적으로 피드백을 요청 및 수용하는 자세를 보이며 팀원의 의견을 반영해왔습니다.\n서로의 부족한 부분을 잡아주고 보완해주며 건설적인 협업이 되었습니다.\n\n다음 프로젝트를 위해\n가장 큰 아쉬운 점은 초기 단계에서 팀원이 공동으로 정한 기획서가 부실했다는 점입니다. 컨셉과 메인 줄거리 이외에 세부 줄거리, 분기점, 구성 요소와 등장 오브젝트 등을 구체적으로 정하고 업무 분담이 진행 되었어야 한다고 생각합니다.\n\n계획적이거나 꼼꼼하지 못한 점을 바꿔나가기 위해서는 팀 회의 전에 미리 결정해야 될 사항에 대해서 체크리스트로 확인하는 방법이 필요하다고 생각합니다.\n\n칭찬합시다\n주재형님이 스토리 완성 후 데이터 테이블 입력 전에 먼저 아트팀과 함께 아트 리소스와 매치 해보자고 의견 주셨습니다. 이 과정에서 어느 배경과 표정, 오브젝트를 활용할지 다같이 테이블에 정리하는 시간이 되었으며, 추가로 필요한 리소스를 파악 할 수 있었습니다.\n\n업무 현황을 파악하고 아트와 스토리를 합치는 과정이 막막했는데 먼저 방향을 잡아준 점에 대해서 기획을 이끌어가는 모습을 보여주었습니다.\n\n자유로운 한마디\n우유부단하고 모두의 의견을 듣는다고 결정하지 못하는 등의 미숙한 팀장이었습니다. 훌룡한 팀원들이 저의 단점을 보완하고 노력해주어서 좋은 결과물이 나왔다고 생각합니다. 다음에 팀장이 된다면 지금보다는 잘 할 수 있도록 이번의 경험을 밑거름 삼겠습니다. 다만, 리더에 역량은 아직 부족하다고 생각합니다."
  },
  {
    "retroId": "retro-08de5c53711c",
    "phase": "2차 프로젝트",
    "date": "2026-02-27",
    "originalDate": "2026-02-27",
    "submittedAt": "2026-02-27T17:22:07.876000",
    "detail": "기획에 대하여\n이번 프로젝트에서 작성한 기획서는 협업 팀원 맞춤용 이었습니다. 개발자와 주로 함께 협업한 용준님이 이해 하시고 활용하기 편한 방향으로 생각하여 제작하였기에 제 기준으로 이해하기 쉬운 기획서는 아니었다고 생각합니다. \n\n그래도 데이터 테이블 형식을 분석하고 활용하면서 새로운 양식으로 제 생각을 담아내는 법을 연습 할 수 있었던 시간이었습니다. \n\n다음에는 독스나 피피티를 활용하여 가독성을 챙기는 방향으로 테이블 작업과 병행하고자 합니다.\n\n협업에 대하여\n프로젝트 진행에서 현실적인 측면을 고려했습니다. \n사전에 버그와 기능 개선 개발을 담당하기로 했던 제가 개발에서 나오게 되면서 팀장님의 1인 개발과 PM이 병행되는 상황이 되었습니다. 이에 대한 현실적인 완성을 위해 개발 취소되는 요소들이 많았습니다.\n\n의외로 큰 볼륨의 시스템 (펫, 증강 등)에 대한 취소는 기획 담당과 원활한 합의가 있었지만, 적의 HP 바, 코인 획득 UI, 웨이브 제한 시간 표시 등 인게임 내 세부적인 요소에 대해서 합의에 시간이 길었습니다.\n\n다음 프로젝트를 위해\n가장 이상적인 팀 작업을 기준으로 보면 업무 분담이 큰 원인이라고 생각됩니다.\n연휴라는 자율적인 업무 기간, PM을 할 수 없는 리더의 조건이 겹쳐서 손이 비면 일이 생기고 붙들고 있으면 일이 없는 팀이었다고 생각합니다. 손이 느린 팀원과 빠른 팀원, 각자의 상황과 속도를 고려하여 업무의 볼륨과 마감 기한이 있었어야 한다고 생각합니다. \n\n돌이켜 생각해보면 제가 맡은 일을 다른 팀원들에게 분업하고 PM이나 개발 하나를 보조 했으면 좋았겠다고 생각합니다.\n생각보다 게임의 볼륨과 컨텐츠가 커져서 조급함을 느껴 시야가 좁아졌다고 생각합니다. 문제의 원인과 원인에 직접적인 영향을 끼치는 것이 무엇인지 분리해서 생각하는 법의 필요성을 체감할 수 있었습니다.\n\n칭찬합시다\n용준님을 칭찬하고 싶습니다. 처음부터 많이 어려워하시고 방향을 못 잡으셔서 같이 많이 이야기하게 되었습니다. 용준님의 속도와 방법에 맞춰 대화하며 그만의 장점을 알 수 있고 어떤 점을 고민하는 지 알 수 있었습니다. 오래 같이 작업하지는 못했지만 다음에 또 하게 된다면 더 좋은 퍼포먼스가 나올 것이라 기대하게 됩니다.\n레퍼런스 게임 분석을 메인으로 담당하시며 쿨타임, 연사 사이클 속도, 타이핑 난이도 등 밸런싱 과정에서 기초적인 틀을 잡을 수 있었습니다. 그리고 QA를 진행해주시면서 생각지도 못한 방법으로 진행하며 버그를 발견하거나 오버 파워 요소를 찾을 수 있었습니다.\n\n그리고 개발과 PM을 담당한 팀장 형진님도 정말 대단하고 고생하셨습니다.\n\n팀장 선호도 조사\n1.0\n\n이유\n팀장은 기본적으로 프로젝트와 팀을 거시적인 관점에서 흐름을 파악하고 관리하는 역할이라고 생각합니다. 저는 그러기엔 나무에 집중하는 사람이라 팀장으로서 봐야하는 큰 흐름을 놓치는 일이 많았습니다. 다른 팀원은 팀장의 권리를 존중하고 신의하기에 의구심이 있어도 넘어가는 경우가 많습니다. 특히, 업무 과정이나 프로젝트 흐름처럼 전체적이고 본질적인 부분에 있어서 일수록 눈에 띄지 않고 잔잔하게 쌓이는 문제라 더욱 위험하다고 생각합니다. 그렇기 때문에 저는 팀장의 역할에는 맞지 않다고 생각합니다.\n\n자유로운 한마디\n밸런싱 담당인데 타이핑 게임을 못해서 후반부 밸런스를 체감하지 못하였습니다. 팀원 후기와 데이터 값만 보며 추측하는데 직접 플레이하고 다양한 경우를 해보면서 여러 데이터를 반영하지 못한 것이 아쉽습니다."
  }
]
