[
  {
    "checkinId": "checkin-0c50cf526d45",
    "phase": "1차 프로젝트",
    "date": "2026-01-20",
    "originalDate": "2026-01-20",
    "submittedAt": "2026-01-20T17:55:48.207000",
    "team": "9팀",
    "workText": "0.25",
    "noteText": "13세 이용가 이슈로 진행 중이던 부분을 폐기를 많이 해야 했다.",
    "onTime": true
  },
  {
    "checkinId": "checkin-921c56bce734",
    "phase": "1차 프로젝트",
    "date": "2026-01-21",
    "originalDate": "2026-01-21",
    "submittedAt": "2026-01-21T17:53:14.150000",
    "team": "9팀",
    "workText": "0.75",
    "noteText": "전반적으로 완만하게 잘 진행되고 있다. 분위기도 좋음",
    "onTime": true
  },
  {
    "checkinId": "checkin-ef15478ce057",
    "phase": "1차 프로젝트",
    "date": "2026-01-22",
    "originalDate": "2026-01-22",
    "submittedAt": "2026-01-22T18:00:44.958000",
    "team": "9팀",
    "workText": "0.75",
    "noteText": "각자의 작업물을 합치는 과정이 생각보다 힘들다는 걸 느꼈다.",
    "onTime": true
  },
  {
    "checkinId": "checkin-bf91ba8dfd59",
    "phase": "1차 프로젝트",
    "date": "2026-01-23",
    "originalDate": "2026-01-23",
    "submittedAt": "2026-01-23T18:01:56.410000",
    "team": "9팀",
    "workText": "0.75",
    "noteText": "생각보다 많이 힘듭니다",
    "onTime": true
  },
  {
    "checkinId": "checkin-45afafa8d9be",
    "phase": "2차 프로젝트",
    "date": "2026-02-13",
    "originalDate": "2026-02-13",
    "submittedAt": "2026-02-13T17:58:21.842000",
    "team": "11팀",
    "workText": "일정 조율, 규칙 설정, 역할 배분, 개인별 기획안 발표, 기획안 채택, 아트 방향성 결정, 시스템 큰 틀 잡",
    "noteText": "순조롭게 진행되고 있다",
    "onTime": true
  },
  {
    "checkinId": "checkin-b8afdd9d4483",
    "phase": "2차 프로젝트",
    "date": "2026-02-19",
    "originalDate": "2026-02-19",
    "submittedAt": "2026-02-19T17:52:49.401000",
    "team": "11팀",
    "workText": "시소 구현/구슬 쌓기 구현/시소 기울기 구현",
    "noteText": "다들 열심히 하고 있습니다",
    "onTime": true
  },
  {
    "checkinId": "checkin-24eecdb32274",
    "phase": "2차 프로젝트",
    "date": "2026-02-20",
    "originalDate": "2026-02-20",
    "submittedAt": "2026-02-20T17:58:03.906000",
    "team": "11팀",
    "workText": "물리 시스템 리팩토링/UI 작업 시작",
    "noteText": "다들 열심히 하십니다",
    "onTime": true
  },
  {
    "checkinId": "checkin-cb43d63a5d84",
    "phase": "2차 프로젝트",
    "date": "2026-02-25",
    "originalDate": "2026-02-25",
    "submittedAt": "2026-02-25T18:59:37.196000",
    "team": "11팀",
    "workText": "BGM 삽입/게임배경, 캐릭터 배경, BGM을 sequence마다 전환/황금구슬 기믹 추가/컷씬에 대한 논의/인트로 영상에 대한 논의",
    "noteText": "이정도면 잘 진행되고 있는 것 같습니다\n다들 열심히 해 주셔서 좋습니다",
    "onTime": true
  },
  {
    "checkinId": "checkin-8258b4f837f7",
    "phase": "2차 프로젝트",
    "date": "2026-02-26",
    "originalDate": "2026-02-26",
    "submittedAt": "2026-02-26T17:59:46.750000",
    "team": "11팀",
    "workText": "엔딩 넣기/토크 조절/카르마 보정/초상화 작업/나이 다듬기/경험치 UI 변경/ending intro 순환구조/plankmove 버그처리",
    "noteText": "힘듭니다",
    "onTime": true
  },
  {
    "checkinId": "checkin-1df87954a88e",
    "phase": "3차 프로젝트",
    "date": "2026-03-18",
    "originalDate": "2026-03-18",
    "submittedAt": "2026-03-18T18:01:40.958000",
    "team": "4팀",
    "workText": "컨셉 기획/시스템 기획 시작",
    "noteText": "순조롭게 잘 되고 있습니다",
    "onTime": true
  },
  {
    "checkinId": "checkin-f09957feba8a",
    "phase": "3차 프로젝트",
    "date": "2026-03-19",
    "originalDate": "2026-03-19",
    "submittedAt": "2026-03-20T10:37:21.475000",
    "team": "4팀",
    "workText": "시스템 기획서 작성/프로토타입 개발",
    "noteText": "아주 편안합니다",
    "onTime": false
  },
  {
    "checkinId": "checkin-515cd5aa07b3",
    "phase": "3차 프로젝트",
    "date": "2026-03-20",
    "originalDate": "2026-03-20",
    "submittedAt": "2026-03-20T17:53:25.921000",
    "team": "4팀",
    "workText": "기획 리뷰/플로우차트 작성",
    "noteText": "좋습니다",
    "onTime": true
  },
  {
    "checkinId": "checkin-7708b75bb5db",
    "phase": "3차 프로젝트",
    "date": "2026-03-23",
    "originalDate": "2026-03-23",
    "submittedAt": "2026-03-23T17:41:07.949000",
    "team": "4팀",
    "workText": "데이터 테이블 작업",
    "noteText": "피곤합니다",
    "onTime": true
  },
  {
    "checkinId": "checkin-ae3c6cd6fd69",
    "phase": "3차 프로젝트",
    "date": "2026-03-24",
    "originalDate": "2026-03-24",
    "submittedAt": "2026-03-24T17:41:49.515000",
    "team": "4팀",
    "workText": "데이터 테이블 검수",
    "noteText": "아주 좋습니다",
    "onTime": true
  },
  {
    "checkinId": "checkin-50947fab7dd2",
    "phase": "3차 프로젝트",
    "date": "2026-03-25",
    "originalDate": "2026-03-25",
    "submittedAt": "2026-03-25T17:49:20.569000",
    "team": "4팀",
    "workText": "식당/손님 데이터 테이블 설계/검수 완료",
    "noteText": "순조롭습니다",
    "onTime": true
  },
  {
    "checkinId": "checkin-b2dada23f48f",
    "phase": "3차 프로젝트",
    "date": "2026-03-26",
    "originalDate": "2026-03-26",
    "submittedAt": "2026-03-26T17:37:18.609000",
    "team": "4팀",
    "workText": "번역 작업/fish data와 recipe data item 추가",
    "noteText": "편안합니다",
    "onTime": true
  },
  {
    "checkinId": "checkin-9c56f7ef2ab6",
    "phase": "3차 프로젝트",
    "date": "2026-03-27",
    "originalDate": "2026-03-27",
    "submittedAt": "2026-03-27T17:53:28.109000",
    "team": "4팀",
    "workText": "localization 완료/밸런스 기획 시작",
    "noteText": "팀 내 작업 노선의 정리가 필요한 거 같습니다.",
    "onTime": true
  },
  {
    "checkinId": "checkin-d6e0294910bf",
    "phase": "3차 프로젝트",
    "date": "2026-03-30",
    "originalDate": "2026-03-30",
    "submittedAt": "2026-03-30T17:32:55.205000",
    "team": "4팀",
    "workText": "밸런스 작업/시스템 구멍 채우기",
    "noteText": "힘드네용",
    "onTime": true
  },
  {
    "checkinId": "checkin-82abe22fc30d",
    "phase": "3차 프로젝트",
    "date": "2026-03-31",
    "originalDate": "2026-03-31",
    "submittedAt": "2026-03-31T17:32:07.822000",
    "team": "4팀",
    "workText": "식당 업그레이드/손님 pay 명세 작성",
    "noteText": "고생 많으십니다",
    "onTime": true
  },
  {
    "checkinId": "checkin-2c7d9e09665a",
    "phase": "3차 프로젝트",
    "date": "2026-04-01",
    "originalDate": "2026-04-01",
    "submittedAt": "2026-04-01T17:58:29.440000",
    "team": "4팀",
    "workText": "밸런스 작업/아트 리소스 관련 논의",
    "noteText": "수고 많으십니다",
    "onTime": true
  },
  {
    "checkinId": "checkin-c5e3a7d8bdd8",
    "phase": "3차 프로젝트",
    "date": "2026-04-02",
    "originalDate": "2026-04-02",
    "submittedAt": "2026-04-02T22:32:53.725000",
    "team": "4팀",
    "workText": "게임 사이클 밸런스 완료/재화 밸런스 작업중",
    "noteText": "수고 많으십니다",
    "onTime": true
  },
  {
    "checkinId": "checkin-6ab449ed8d4f",
    "phase": "3차 프로젝트",
    "date": "2026-04-03",
    "originalDate": "2026-04-03",
    "submittedAt": "2026-04-03T17:35:30.731000",
    "team": "4팀",
    "workText": "데이터테이블 최신화/검수/재화 밸런싱 완료",
    "noteText": "고생하십니다",
    "onTime": true
  },
  {
    "checkinId": "checkin-aa48b46e8586",
    "phase": "3차 프로젝트",
    "date": "2026-04-06",
    "originalDate": "2026-04-06",
    "submittedAt": "2026-04-06T17:31:05.194000",
    "team": "4팀",
    "workText": "이미지 리소스 최적화/밸런스 기획서 작성",
    "noteText": "수고하셨습니다",
    "onTime": true
  },
  {
    "checkinId": "checkin-9c7648d95b06",
    "phase": "3차 프로젝트",
    "date": "2026-04-07",
    "originalDate": "2026-04-07",
    "submittedAt": "2026-04-07T17:50:29.599000",
    "team": "4팀",
    "workText": "대기/QA",
    "noteText": "수고하셨습니다",
    "onTime": true
  },
  {
    "checkinId": "checkin-d5dd7df09942",
    "phase": "3차 프로젝트",
    "date": "2026-04-08",
    "originalDate": "2026-04-08",
    "submittedAt": "2026-04-08T17:44:52.218000",
    "team": "4팀",
    "workText": "QA",
    "noteText": "허허이~",
    "onTime": true
  }
]
